mongey/__init__.py
mongey/config.py
mongey/context.py
mongey/db.py
mongey/decorators.py
mongey/errors.py
mongey/types.py
mongey/util.py
mongey/cache/__init__.py
mongey/cache/abc.py
mongey/cache/memcached.py
mongey/cache/nocache.py
mongey/cache/request_local.py
mongey/cache/simple.py
mongey/cache/trace.py
mongey/models/__init__.py
mongey/models/base_model.py
mongey/models/counter.py
mongey/models/fields.py
mongey/models/index.py
mongey/models/meta_model.py
mongey/models/reference.py
mongey/models/storable_model.py
mongey/models/submodel.py
mongey/models/timestamped_model.py
mongey/tests/__init__.py
mongey/tests/mongo_mock_test.py
mongey/tests/test_base_model.py
mongey/tests/test_reference.py
mongey/tests/test_storable_model.py
mongey/tests/test_submodel.py
mongey/tests/test_validators.py
mongey-0.1.9.dist-info/LICENSE
mongey-0.1.9.dist-info/METADATA
mongey-0.1.9.dist-info/WHEEL
mongey-0.1.9.dist-info/top_level.txt
mongey-0.1.9.dist-info/RECORD
