Metadata-Version: 2.2
Name: mongey
Version: 0.1.9
Summary: asynchronous MongoDB ORM
Author-email: Pavel Vorobyev <aquavitale@yandex.ru>
License: MIT
Project-URL: Source, https://github.com/viert/mongey
Keywords: pymongo,mongodb,motor,asyncio
Requires-Python: >=3.11
License-File: LICENSE
Requires-Dist: aiomcache
Requires-Dist: contextvars
Requires-Dist: mongomock_motor
Requires-Dist: motor
Requires-Dist: pymongo
Requires-Dist: pydantic
